MANIFEST.in
setup.cfg
setup.py
jenkins_tools.egg-info/PKG-INFO
jenkins_tools.egg-info/SOURCES.txt
jenkins_tools.egg-info/dependency_links.txt
jenkins_tools.egg-info/requires.txt
jenkins_tools.egg-info/top_level.txt
scripts/chroot_create.sh
scripts/chroot_dispatch.sh
scripts/chroot_update.sh
scripts/delete_jenkins
scripts/generate_jenkins_devel
scripts/generate_jenkins_doc
scripts/generate_jenkins_prerelease
scripts/run_chroot_jenkins_now
scripts/run_chroot_jenkins_periodic
scripts/run_chroot_jenkins_vcs
scripts/run_chroot_local
src/jenkins_tools/__init__.py
src/jenkins_tools/run_jenkins.py
src/jenkins_tools/resources/templates/jenkins_conf.yaml
src/jenkins_tools/resources/templates/jenkins_template.xml
src/jenkins_tools/resources/templates/junit_dummy_ouput_template.xml
src/jenkins_tools/resources/templates/junit_ouput_template.xml
src/jenkins_tools/resources/templates/publisher_extend_notification_recipients.xml
src/jenkins_tools/resources/templates/publisher_notification_on_success.xml