Metadata-Version: 1.1
Name: jenkins-tools
Version: 0.0.67
Summary: A tool for running scripts in a chroot environment on Jenkins or locally
Home-page: http://wiki.ros.org/jenkins_tools
Author: Dirk Thomas
Author-email: dthomas@osrfoundation.org
License: BSD
Download-URL: http://download.ros.org/downloads/jenkins_tools/
Keywords: ROS
Platform: UNKNOWN
Classifier: Programming Language :: Python
Classifier: License :: OSI Approved :: BSD License
